super_scad_thread/ExternalThread.py
super_scad_thread/InternalThread.py
super_scad_thread/Thread.py
super_scad_thread/ThreadProfileCreator.py
super_scad_thread/__init__.py
super_scad_thread/enum/ThreadAnatomy.py
super_scad_thread/enum/ThreadDirection.py
super_scad_thread/enum/ThreadGender.py
super_scad_thread/enum/__init__.py
super_scad_thread/lead_thread/ThreadLeadCreator.py
super_scad_thread/lead_thread/__init__.py
super_scad_thread/lead_thread/external/ExternalThreadLeadCreator.py
super_scad_thread/lead_thread/external/NoneExternalThreadLeadCreator.py
super_scad_thread/lead_thread/external/ScaleInExternalThreadLeadCreator.py
super_scad_thread/lead_thread/external/__init__.py
super_scad_thread/lead_thread/internal/InternalThreadLeadCreator.py
super_scad_thread/lead_thread/internal/NoneInternalThreadLeadCreator.py
super_scad_thread/lead_thread/internal/ScaleInInternalThreadLeadCreator.py
super_scad_thread/lead_thread/internal/__init__.py
super_scad_thread-0.2.0.dist-info/LICENSE
super_scad_thread-0.2.0.dist-info/METADATA
super_scad_thread-0.2.0.dist-info/WHEEL
super_scad_thread-0.2.0.dist-info/RECORD
